django_splitted_input/__init__.py
django_splitted_input/apps.py
django_splitted_input/static/django_splitted_input/css/input.css
django_splitted_input/static/django_splitted_input/css/input.css.map
django_splitted_input/static/django_splitted_input/css/input.scss
django_splitted_input/static/django_splitted_input/js/input.js
django_splitted_input/templates/django_splitted_input/widget.html
django_splitted_input/widgets.py
django_splitted_input-0.1.1.dist-info/WHEEL
django_splitted_input-0.1.1.dist-info/METADATA
django_splitted_input-0.1.1.dist-info/RECORD
