Metadata-Version: 2.1
Name: django-splitted-input
Version: 0.1.1
Summary: A widget to have a django text input splitted into multiple HTML inputs.
Home-page: https://edugit.org/AlekSIS/libs/django-splitted-input
Keywords: django,widget
Author: Julian Leucker
Author-email: leuckerj@gmail.com
Requires-Python: >=3.7,<4.0
Classifier: Environment :: Web Environment
Classifier: Framework :: Django :: 3.1
Classifier: Intended Audience :: Developers
Classifier: Programming Language :: Python :: 3
Classifier: Programming Language :: Python :: 3.7
Classifier: Programming Language :: Python :: 3.8
Classifier: Programming Language :: Python :: 3.9
Classifier: Topic :: Internet :: WWW/HTTP :: WSGI :: Application
Classifier: Topic :: Software Development :: Libraries :: Application Frameworks
Classifier: Typing :: Typed
Requires-Dist: Django (>=3.1,<4.0)
Project-URL: Repository, https://edugit.org/AlekSIS/libs/django-splitted-input
